{
  "$type": "ThunderRoad.CreatureTable, ThunderRoad",
  "id": "Jedi",
  "version": 1,
  "description": null,
  "linkedToGenderRatio": false,
  "drops": [
    {
      "reference": "Table",
      "referenceID": "ForceSensitive",
      "overrideFaction": true,
      "factionID": 4,
      "overrideContainer": true,
      "overrideContainerID": "Jedi",
      "overrideBrain": true,
      "overrideBrainID": "ForceSensitive",
      "probabilityWeights": [
        8,
        8,
        8,
        8,
        8
      ]
    },
    {
      "reference": "Table",
      "referenceID": "ForceSensitive",
      "overrideFaction": true,
      "factionID": 4,
      "overrideContainer": true,
      "overrideContainerID": "JediDual",
      "overrideBrain": true,
      "overrideBrainID": "ForceSensitive",
      "probabilityWeights": [
        1,
        1,
        1,
        1,
        1
      ]
    }
  ]
}