{
  "$type": "ThunderRoad.ContainerData, ThunderRoad",
  "id": "Gamorrean",
  "version": 1,
  "displayName": "",
  "prefabName": "",
  "contents": [
    {
      "reference": "Table",
      "referenceID": "GamorreanFeet",
      "customDataList": []
    },
    {
      "reference": "Table",
      "referenceID": "GamorreanTorso",
      "customDataList": []
    },
	{
      "reference": "Table",
      "referenceID": "GamorreanHead",
      "customDataList": []
    },
    {
      "reference": "Table",
      "referenceID": "GamorreanWeapon",
      "state": {
        "$type": "ThunderRoad.ContentStateHolder, ThunderRoad",
        "holderName": "BackRight"
      },
      "customDataList": []
    }
  ]
}